<aars><explodeData><aar>Assets/Plugins/Android\appcompat-v7-23.1.1.aar</aar><modificationTime>2016-07-06T13:27:09.1534504-05:00</modificationTime><explode>false</explode><bundleId>com.smallcatstudios.raverun</bundleId><path>Assets/Plugins/Android\appcompat-v7-23.1.1.aar</path></explodeData><explodeData><aar>Assets/Plugins/Android\play-services-ads-9.2.0.aar</aar><modificationTime>2016-07-06T13:27:48.4528961-05:00</modificationTime><explode>false</explode><bundleId>com.smallcatstudios.raverun</bundleId><path>Assets/Plugins/Android\play-services-ads-9.2.0.aar</path></explodeData><explodeData><aar>Assets/Plugins/Android\play-services-ads-lite-9.2.0.aar</aar><modificationTime>2016-07-06T13:27:50.2693711-05:00</modificationTime><explode>false</explode><bundleId>com.smallcatstudios.raverun</bundleId><path>Assets/Plugins/Android\play-services-ads-lite-9.2.0.aar</path></explodeData><explodeData><aar>Assets/Plugins/Android\play-services-base-9.2.0.aar</aar><modificationTime>2016-07-06T13:27:50.7705180-05:00</modificationTime><explode>false</explode><bundleId>com.smallcatstudios.raverun</bundleId><path>Assets/Plugins/Android\play-services-base-9.2.0.aar</path></explodeData><explodeData><aar>Assets/Plugins/Android\play-services-basement-9.2.0.aar</aar><modificationTime>2016-07-06T13:27:51.6947519-05:00</modificationTime><explode>false</explode><bundleId>com.smallcatstudios.raverun</bundleId><path>Assets/Plugins/Android\play-services-basement-9.2.0.aar</path></explodeData><explodeData><aar>Assets/Plugins/Android\play-services-clearcut-9.2.0.aar</aar><modificationTime>2016-07-06T13:27:49.8105904-05:00</modificationTime><explode>false</explode><bundleId>com.smallcatstudios.raverun</bundleId><path>Assets/Plugins/Android\play-services-clearcut-9.2.0.aar</path></explodeData><explodeData><aar>Assets/Plugins/Android\play-services-gass-9.2.0.aar</aar><modificationTime>2016-07-06T13:27:51.1059299-05:00</modificationTime><explode>false</explode><bundleId>com.smallcatstudios.raverun</bundleId><path>Assets/Plugins/Android\play-services-gass-9.2.0.aar</path></explodeData><explodeData><aar>Assets/Plugins/Android\play-services-tasks-9.2.0.aar</aar><modificationTime>2016-07-06T13:27:49.6883265-05:00</modificationTime><explode>false</explode><bundleId>com.smallcatstudios.raverun</bundleId><path>Assets/Plugins/Android\play-services-tasks-9.2.0.aar</path></explodeData><explodeData><aar>Assets/Plugins/Android\support-v4-23.1.1.aar</aar><modificationTime>2016-07-06T13:27:03.9116524-05:00</modificationTime><explode>false</explode><bundleId>com.smallcatstudios.raverun</bundleId><path>Assets/Plugins/Android\support-v4-23.1.1.aar</path></explodeData></aars>